pyproofpoint/__init__.py
pyproofpoint/proofpoint.py
pyproofpoint-1.0.2.dist-info/LICENSE
pyproofpoint-1.0.2.dist-info/METADATA
pyproofpoint-1.0.2.dist-info/WHEEL
pyproofpoint-1.0.2.dist-info/top_level.txt
pyproofpoint-1.0.2.dist-info/RECORD
