Metadata-Version: 2.1
Name: pyproofpoint
Version: 1.0.2
Summary: A python wrapper for proofpoint's threat insight API
Home-page: https://github.com/Derekt2/PyProofpoint
Author: Derek Thomas2
Author-email: derek.e.thomas@biola.edu
Maintainer: Derek Thomas2
License: UNKNOWN
Platform: UNKNOWN
Classifier: Programming Language :: Python :: 3
Classifier: License :: OSI Approved :: MIT License
Classifier: Operating System :: OS Independent
Classifier: Intended Audience :: Science/Research
Classifier: Intended Audience :: Telecommunications Industry
Classifier: Intended Audience :: Information Technology
Classifier: Topic :: Security
Classifier: Topic :: Internet
Requires-Python: >=3.5
Requires-Dist: requests
